ShejimoshiBaojiaoBuBaohui/README.md
ShejimoshiBaojiaoBuBaohui/__init__.py
ShejimoshiBaojiaoBuBaohui/__main__.py
ShejimoshiBaojiaoBuBaohui/file.epub
ShejimoshiBaojiaoBuBaohui/index.html
ShejimoshiBaojiaoBuBaohui/css/__init__.py
ShejimoshiBaojiaoBuBaohui/css/annotations.css
ShejimoshiBaojiaoBuBaohui/css/main.css
ShejimoshiBaojiaoBuBaohui/css/normalize.css
ShejimoshiBaojiaoBuBaohui/css/popup.css
ShejimoshiBaojiaoBuBaohui/font/__init__.py
ShejimoshiBaojiaoBuBaohui/font/fontello.eot
ShejimoshiBaojiaoBuBaohui/font/fontello.svg
ShejimoshiBaojiaoBuBaohui/font/fontello.ttf
ShejimoshiBaojiaoBuBaohui/font/fontello.woff
ShejimoshiBaojiaoBuBaohui/img/__init__.py
ShejimoshiBaojiaoBuBaohui/img/annotator-glyph-sprite.png
ShejimoshiBaojiaoBuBaohui/img/annotator-icon-sprite.png
ShejimoshiBaojiaoBuBaohui/img/apple-touch-icon.png
ShejimoshiBaojiaoBuBaohui/img/cancelfullscreen.png
ShejimoshiBaojiaoBuBaohui/img/close.png
ShejimoshiBaojiaoBuBaohui/img/fullscreen.png
ShejimoshiBaojiaoBuBaohui/img/loader.gif
ShejimoshiBaojiaoBuBaohui/img/menu-icon.png
ShejimoshiBaojiaoBuBaohui/img/save.png
ShejimoshiBaojiaoBuBaohui/img/saved.png
ShejimoshiBaojiaoBuBaohui/img/settings-s.png
ShejimoshiBaojiaoBuBaohui/img/settings.png
ShejimoshiBaojiaoBuBaohui/img/star.png
ShejimoshiBaojiaoBuBaohui/js/__init__.py
ShejimoshiBaojiaoBuBaohui/js/epub.js
ShejimoshiBaojiaoBuBaohui/js/epub.min.js
ShejimoshiBaojiaoBuBaohui/js/epub.min.map
ShejimoshiBaojiaoBuBaohui/js/hooks.min.js
ShejimoshiBaojiaoBuBaohui/js/hooks.min.map
ShejimoshiBaojiaoBuBaohui/js/reader.js
ShejimoshiBaojiaoBuBaohui/js/reader.js.map
ShejimoshiBaojiaoBuBaohui/js/reader.min.js
ShejimoshiBaojiaoBuBaohui/js/reader.min.map
ShejimoshiBaojiaoBuBaohui/js/hooks/__init__.py
ShejimoshiBaojiaoBuBaohui/js/hooks/extensions/__init__.py
ShejimoshiBaojiaoBuBaohui/js/hooks/extensions/highlight.js
ShejimoshiBaojiaoBuBaohui/js/libs/__init__.py
ShejimoshiBaojiaoBuBaohui/js/libs/jquery.min.js
ShejimoshiBaojiaoBuBaohui/js/libs/localforage.min.js
shejimoshi_baojiao_bu_baohui-2024.3.2.0.dist-info/METADATA
shejimoshi_baojiao_bu_baohui-2024.3.2.0.dist-info/WHEEL
shejimoshi_baojiao_bu_baohui-2024.3.2.0.dist-info/entry_points.txt
shejimoshi_baojiao_bu_baohui-2024.3.2.0.dist-info/top_level.txt
shejimoshi_baojiao_bu_baohui-2024.3.2.0.dist-info/RECORD
